[
  {
    "first_name": "Aiden",
    "last_name": "Radinksky",
    "email": "asradinsky@gmail.com",
    "password": "pass1234",
    "number_seats": 0,
    "movie_id": null
  },
  {
    "first_name": "Iris",
    "last_name": "Valle",
    "email": "iris.valle.design@gmail.com",
    "password": "pass1235",
    "number_seats": 0,
    "movie_id": null
  },
  {
    "first_name": "Joey",
    "last_name": "Kouneski",
    "email": "joeykouneski@gmail.com",
    "password": "pass1236",
    "number_seats": 0,
    "movie_id": null
  },
  {
    "first_name": "Reggie",
    "last_name": "Mace",
    "email": "reginaldmace36@gmail.com",
    "password": "pass1237",
    "number_seats": 0,
    "movie_id": null
  }
]
